{
  "english": "beautiful",
  "phat_am": "",
  "list_english": [
    {
      "type_word": "adjective",
      "list_definition": [
        {
          "mean_english": "đẹp",
          "world_new": [],
          "list_ex_of_definition": [
            {
              "ex_of_definition": "a beautiful woman"
            },
            {
              "ex_of_definition": "Those roses are beautiful."
            }
          ]
        }
      ]
    }
  ],
  "list_ex_of_english": [
    "This is a very beautiful and useful book.",
    "Therefore, accompanied by their spouses and other ethically challenged luminaries, they settled in a beautiful international site and decided to rewrite their document.",
    "The voices are beautiful and well suited to the roles.",
    "But why is this more beautiful than the classical elegance of pre-planned harmony.",
    "Every individual entity is beautiful, perhaps - but that leaves ugliness in plenty to be transformed or salvaged.",
    "Wonder at any natural scene that is beautiful.",
    "An extremely beautiful photographic record of a row of vortices in the case of 8 = 75\" is shown in figure 15.",
    "Her beautiful dream will, of course, be destroyed; violence, literal and verbal, will mock it."
  ],
  "list_see_also": [],
  "list_browse": [
    "beaten",
    "beater",
    "beating",
    "beautician",
    "beautiful",
    "beautifully",
    "beautify",
    "beauty",
    "beauty queen"
  ]
}